CPU/assert.v
`define assert(sig, val) \
    if (sig !== val) begin \
        $display("ASSERTION FAILED in %m: sig != %0d [original value %0d] in line %0d", val, sig, `__LINE__); \
        $finish; \
    end

CPU Test/ALU/alu.v
`timescale 1ns/100ps
//alu module for RISCV procr
//
module alu(DATA1, DATA2, RESULT,BRANCH,SELECT);			
	input [31:0]DATA1;						//input of Data 1 value
	input [31:0]DATA2;						//input of data 2 value
	input [4:0]SELECT;						//alu opecode
	output reg [31:0]RESULT;					//output for result fot the operation
	output reg BRANCH;
	
	//alu results
	wire[31:0] 	RES_AND,	// 1. and
			RES_OR,		// 2. or
			RES_XOR,	// 3, xor
			RES_ADD,
			RES_SUB,
			RES_SLL,	//shift left logical
			RES_SRL,	//shift right logical
			RES_SRA,  	//shift right arithmatic
			RES_FWD,	//forward
			RES_MUL,	//multiplication
			RES_MULH,	//multiplication higer signed * signed
			RES_MULHU,	//multiplication higher unsigned * unsigned
			RES_MULHSU,	//mul higher signed * unsigned
			RES_DIV,	//Divition
			RES_REM,	//Remainder
			RES_SLT,	//Less than
			RES_SLTU	//less thank unsigned
			;
			
	//for branch outputs
	wire BR_BEQ, BR_BNE, BR_BLT, BR_BGE, BR_BLTU, BR_BGEU;
	//AND,OR,XOR operations with 1 time unit delay
	//these are bitwise operations
	assign #3 RES_AND = DATA1 & DATA2;
	assign #3 RES_OR  = DATA1 | DATA2;
	assign #3 RES_XOR = DATA1 ^ DATA2;
	
	//forwad operation
	assign #3 RES_FWD = DATA2;
	
	//ADD, SUB operations with 2 time unit delay
	assign #3 RES_ADD = DATA1+DATA2;
	assign #3 RES_SUB = DATA1-DATA2;
	
	//shift operations with 1 time unit delay
	assign #3 RES_SLL = DATA1 << DATA2;
	assign #3 RES_SRL = DATA1 >> DATA2;
	assign #3 RES_SRA = DATA1 >>> DATA2;

	//multiplication and divition operations
	assign #3 RES_MUL = DATA1 * DATA2;
	assign #3 RES_MULH =  $signed(DATA1) * $signed(DATA2);
	assign #3 RES_MULHSU = $signed(DATA1) * $unsigned(DATA2);
	assign #3 RES_MULHU = $unsigned(DATA1) * $unsigned(DATA2);	
	assign #3 RES_DIV = DATA1 / DATA2;
	
	//Remainder operaion
	assign #3 RES_REM = $signed(DATA1) % $signed(DATA2);
	assign #3 RES_REMU = $unsigned(DATA1) % $unsigned(DATA2);
	
	//less than operation
	assign #3 RES_SLT = ($signed(DATA1) < $signed(DATA2)) ? 1'b1 : 1'b0;
	assign #3 RES_SLTU = ($unsigned(DATA1) < $unsigned(DATA2)) ? 1'b1 : 1'b0;
	
	
	//Branch signals
	assign #3 BR_BEQ = (DATA1 == DATA2);
	assign #3 BR_BNE = (DATA1 != DATA2);
	assign #3 BR_BLT = ($signed(DATA1) < $signed(DATA2));
	assign #3 BR_BGE = ($signed(DATA1) >= $signed(DATA2));
	assign #3 BR_BLTU = DATA1 < DATA2;
	assign #3 BR_BGEU = DATA1 >= DATA2;
	
	
	//reg BEQ;
	always @ (DATA1,DATA2,SELECT)		//done it whe there is a change in values and do the operation with 1 time interval delay
	//2 time unit redelay added becuase the is worse 2 time unit delay from pipeline to alu
	begin #3
    	case(SELECT)

    	//0. ADD operation 
    	5'b00000:  #1 RESULT = RES_ADD; 
    	//1. SLL operation - Shift Left Logic
    	5'b00001:  #1 RESULT = RES_SLL;
    	//2. set les than
    	5'b00010:  #1 RESULT = RES_SLT;
    	//3. set less than unsigned
    	5'b00011:  #1 RESULT = RES_SLTU;
    	//4. XOR
    	5'b00100:  #1 RESULT = RES_XOR; 
    	//5. Shift Right Logic
    	5'b00101:  #1 RESULT = RES_SRL;
    	//6. OR
    	5'b00110:  #1 RESULT = RES_OR; 
    	//7. AND
    	5'b00111:  #1 RESULT = RES_AND;
		//16. Subtract
		5'b10000:  #1 RESULT = RES_SUB;
		//17. 
		5'b10001:  #1 RESULT = RES_SUB;
		//18. 
		5'b10010: RESULT = 0;
		//19. 
		5'b10011: RESULT = 0;
		//20. 
		5'b10100: RESULT = 0;
		//21. SRA = Shift right arithmaic
		5'b10101: #1 RESULT = RES_SRA;
		//22. 
		5'b10110: RESULT = 0;
		//23. 
		5'b10111: RESULT = 0;
		//24. Multiplication
		5'b11000: #1 RESULT = RES_MUL;
		//25. Multiplication high signed
		5'b11001: #1 RESULT = RES_MULH;
		//26. Multiplication high signed * unsigned
		5'b11010: #1 RESULT = RES_MULHSU;
		//27. Multiplication high unsigned
		5'b11011: #1 RESULT = RES_MULHU;
		//28. DIV DIvition
		5'b11100: #1 RESULT = RES_DIV;
		//29. REM signed Remainder
		5'b11101: #1 RESULT = RES_REM;
		//30. Forward
		5'b11110: #1 RESULT = RES_FWD;
		//31. REM Unsigned 
		5'b11111: #1 RESULT = RES_REMU;
        default: 
            RESULT = 0; 
        endcase
		
		//Seting branch val
		case(SELECT)
		//8.
    	5'b01000: #1 BRANCH = BR_BEQ;
		//9
		5'b01001: #1 BRANCH = BR_BNE;
		//10
		5'b01010: BRANCH = 0;
		//11
		5'b01011: BRANCH = 0;
		//12
		5'b01100: #1 BRANCH = BR_BLT;
		//13. 
		5'b01101: #1 BRANCH = BR_BGE;
		//14
		5'b01110: #1 BRANCH = BR_BLTU;
		//15
		5'b01111: #1 BRANCH = BR_BGEU;
		//17. 
		5'b10001:  #1 BRANCH = 1;
		default: 
            BRANCH = 0;
		endcase
    end
endmodule

CPU Test/ALU/alu_testBench.v
/*Test bench for alu testing
compile : iverilog -o alu_testBench alu_TestBench.v
run: vvp alu_testBench
gtkwave : gtkwave alu_wave.vcd
*/
`include "../assert.v" 
`include "alu.v"
`timescale 1ns/100ps
module alu_tb;

    reg CLK, RESET;
    wire [31:0] RESULT;
	wire BRANCH;
    reg [31:0] DATA1, DATA2;
    reg [4:0] SELECT;

    alu myalu(DATA1, DATA2, RESULT, BRANCH, SELECT);
    
    initial begin
        CLK = 1'b0;
	$dumpfile("alu_wave.vcd");
	$dumpvars(0, alu_tb);
        #1
        RESET = 1'b1;

        #3
        RESET = 1'b0;

        //Test 1: addition
		SELECT = 5'b0;
		DATA1 = 32'd5;
		DATA2 = 32'd10;

    	// wait for add to happen
    	#3
    	`assert(RESULT, 32'd15);
    
    	$display("TEST 0 : ADD Passed!");
		
		//Test 2: shift lest logical
		#1
		SELECT = 5'b00001;
		DATA1 = 32'd5;
		DATA2 = 32'd2;
		
		#3
    	`assert(RESULT, 32'd20);
    
    	$display("TEST 1 : Shift Left Logical Passed!");
		
		//Test 3: set less than
		#1
		SELECT = 5'b00010;
		DATA1 = 32'd6;
		DATA2 = 32'b11111111111111111111111111111110; //-2
		
		#3
    	`assert(RESULT, 32'd0);
    
    	$display("TEST 2 : Set Less Than Passed!");
		
		//Test 4: set less than unsingned
		#1
		SELECT = 5'b00011;
		DATA1 = 32'd6;
		DATA2 = 32'b11111111111111111111111111111110;
		
		#3
    	`assert(RESULT, 32'd1);
    
    	$display("TEST 4 : Set Less Than Unsigned Passed!");
		
		//Test 5: Bitwise XOR
		#1
		SELECT = 5'b00100;
		DATA1 = 32'd13;
		DATA2 = 32'd56;
		
		#3
    	`assert(RESULT, 32'd53);
    
    	$display("TEST 5: XOR Passed!");
		
		
		//Test 7: Bitwise OR
		#1
		SELECT = 5'b00110;
		DATA1 = 32'd13;
		DATA2 = 32'd56;
		
		#3
    	`assert(RESULT, 32'd61);
    
    	$display("TEST 7: OR Passed!");
		
		//Test 8: Bitwise AND
		#1
		SELECT = 5'b00111;
		DATA1 = 32'd13;
		DATA2 = 32'd56;
		
		#3
    	`assert(RESULT, 32'd8);
    
    	$display("TEST 7: AND Passed!");
		
		//Test subtraction
		#1
		SELECT = 5'b10000;
		DATA1 = 32'd15;
		DATA2 = 32'd10;
		
		#3
    	`assert(RESULT, 32'd5);
    
    	$display("TEST 7 : SUB Passed!");
		
		//Test BEQ
		#1
		SELECT = 5'b01000;
		DATA1 = 32'd10;
		DATA2 = 32'd10;
		
		#3
    	`assert(BRANCH, 1);
    
    	$display("TEST 8 : BEQ Passed!");
		
		//Test BNE
		#1
		SELECT = 5'b01001;
		DATA1 = 32'd10;
		DATA2 = 32'd11;
		
		#3
    	`assert(BRANCH, 1);
    
    	$display("TEST 9 : BNE Passed!");
		
		//Test BLT
		#1
		SELECT = 5'b01100;
		DATA1 = 32'd10;
		DATA2 = 32'd11;
		
		#3
    	`assert(BRANCH, 1);
    
    	$display("TEST 12 : BLT Passed!");
		
		//Test Multplication
		#1
		SELECT = 5'b11000;
		DATA1 = 32'd50000000000;
		DATA2 = 32'd200;
		
		#3
    	`assert(RESULT, 32'd10000000000000);
    
    	$display(RESULT);
		
		//Test Divition
		#1
		SELECT = 5'b11100;
		DATA1 = 32'd10;
		DATA2 = 32'd2;
		
		#3
    	`assert(RESULT, 32'd5);
    
    	$display("TEST 28 : Divition Passed!");
		
		//Test Remainder
		#1
		SELECT = 5'b11101;
		DATA1 = 32'd27;
		DATA2 = 32'd5;
		
		#3
    	`assert(RESULT, 32'd2);
    
    	$display("TEST 29 : Remainder Passed!");
		

        #500
        $finish;
    end

    // clock genaration.
    always begin
        #4 CLK = ~CLK;
    end

endmodule

CPU Test/ALU/alu_wave.vcd
$date
	Thu Aug 05 13:35:00 2021
$end
$version
	Icarus Verilog
$end
$timescale
	100ps
$end
$scope module alu_tb $end
$var wire 32 ! RESULT [31:0] $end
$var wire 1 " BRANCH $end
$var reg 1 # CLK $end
$var reg 32 $ DATA1 [31:0] $end
$var reg 32 % DATA2 [31:0] $end
$var reg 1 & RESET $end
$var reg 5 ' SELECT [4:0] $end
$scope module myalu $end
$var wire 32 ( DATA1 [31:0] $end
$var wire 32 ) DATA2 [31:0] $end
$var wire 32 * RES_AND [31:0] $end
$var wire 32 + RES_FWD [31:0] $end
$var wire 32 , RES_OR [31:0] $end
$var wire 32 - RES_XOR [31:0] $end
$var wire 5 . SELECT [4:0] $end
$var wire 32 / RES_SUB [31:0] $end
$var wire 32 0 RES_SRL [31:0] $end
$var wire 32 1 RES_SRA [31:0] $end
$var wire 32 2 RES_SLTU [31:0] $end
$var wire 32 3 RES_SLT [31:0] $end
$var wire 32 4 RES_SLL [31:0] $end
$var wire 1 5 RES_REMU $end
$var wire 32 6 RES_REM [31:0] $end
$var wire 32 7 RES_MULHU [31:0] $end
$var wire 32 8 RES_MULHSU [31:0] $end
$var wire 32 9 RES_MULH [31:0] $end
$var wire 32 : RES_MUL [31:0] $end
$var wire 32 ; RES_DIV [31:0] $end
$var wire 32 < RES_ADD [31:0] $end
$var wire 1 = BR_BNE $end
$var wire 1 > BR_BLTU $end
$var wire 1 ? BR_BLT $end
$var wire 1 @ BR_BGEU $end
$var wire 1 A BR_BGE $end
$var wire 1 B BR_BEQ $end
$var reg 1 " BRANCH $end
$var reg 32 C RESULT [31:0] $end
$upscope $end
$upscope $end
$enddefinitions $end
#0
$dumpvars
bx C
xB
xA
x@
x?
x>
x=
bx <
bx ;
bx :
bx 9
bx 8
bx 7
bx 6
x5
bx 4
bx 3
bx 2
bx 1
bx 0
bx /
bx .
bx -
bx ,
bx +
bx *
bx )
bx (
bx '
x&
bx %
bx $
0#
x"
bx !
$end
#10
1&
#20
b0x 3
b0x 2
#40
b1010 %
b1010 )
b101 $
b101 (
b0 '
b0 .
0&
1#
#60
0"
b1111 !
b1111 C
15
b1 3
b1 2
b0 *
b1111 ,
b1111 -
b1010 +
b1111 <
b11111111111111111111111111111011 /
b1010000000000 4
b0 0
b0 1
b110010 :
b110010 9
b110010 8
b110010 7
b0 ;
b101 6
0B
1=
1?
0A
1>
0@
#80
b10 %
b10 )
b1 '
b1 .
0#
#100
b10100 !
b10100 C
b111 ,
b111 -
b0 3
b0 2
b10 +
b111 <
b11 /
b10100 4
b1 0
b1 1
b1010 :
b1010 9
b1010 8
b1010 7
b10 ;
b1 6
0?
1A
0>
1@
#120
b11111111111111111111111111111110 %
b11111111111111111111111111111110 )
b110 $
b110 (
b10 '
b10 .
1#
#140
b0 !
b0 C
b1 2
b110 *
b11111111111111111111111111111110 ,
b11111111111111111111111111111000 -
05
b11111111111111111111111111111110 +
b0 0
b0 1
1>
0@
b100 <
b1000 /
b0 4
b11111111111111111111111111110100 :
b11111111111111111111111111110100 9
b11111111111111111111111111110100 8
b11111111111111111111111111110100 7
b0 ;
b0 6
#160
b11 '
b11 .
0#
#180
b1 !
b1 C
#200
b111000 %
b111000 )
b1101 $
b1101 (
b100 '
b100 .
1#
#220
b110101 !
b110101 C
b1 3
b1000 *
b111101 ,
b110101 -
15
b111000 +
1?
0A
b1000101 <
b11111111111111111111111111010101 /
b1011011000 :
b1011011000 9
b1011011000 8
b1011011000 7
b1101 6
#240
b110 '
b110 .
0#
#260
b111101 !
b111101 C
#280
b111 '
b111 .
1#
#300
b1000 !
b1000 C
#320
b1010 %
b1010 )
b1111 $
b1111 (
b10000 '
b10000 .
0#
#340
b101 !
b101 C
b0 3
b0 2
b1010 *
b1111 ,
b101 -
b1010 +
b11110000000000 4
b1 ;
0?
1A
0>
1@
b11001 <
b101 /
b10010110 :
b10010110 9
b10010110 8
b10010110 7
b101 6
#360
b1010 $
b1010 (
b1000 '
b1000 .
1#
#370
b0 !
b0 C
#380
1"
b1010 ,
b0 -
05
b10100 <
b0 /
b10100000000000 4
b1100100 :
b1100100 9
b1100100 8
b1100100 7
b0 6
1B
0=
#400
b1011 %
b1011 )
b1001 '
b1001 .
0#
#420
b1011 ,
b1 -
b1 3
b1 2
b1011 +
b10101 <
b11111111111111111111111111111111 /
b101000000000000 4
b1101110 :
b1101110 9
b1101110 8
b1101110 7
b0 ;
b1010 6
0B
1=
1?
0A
1>
0@
#440
b1100 '
b1100 .
1#
#480
b11001000 %
b11001000 )
b10100100001110110111010000000000 $
b10100100001110110111010000000000 (
b11000 '
b11000 .
0#
#500
0"
b1001110011100101010000000000000 !
b1001110011100101010000000000000 C
b0 *
b10100100001110110111010011001000 ,
b10100100001110110111010011001000 -
b0 2
b11001000 +
b10100100001110110111010011001000 <
b10100100001110110111001100111000 /
b0 4
b1001110011100101010000000000000 :
b1001110011100101010000000000000 9
b1001110011100101010000000000000 8
b1001110011100101010000000000000 7
b110100100011011110011110 ;
b11111111111111111111111101101000 6
0>
1@
#520
b10 %
b10 )
b1010 $
b1010 (
b11100 '
b11100 .
1#
#540
b101 !
b101 C
b0 3
b10 *
b1010 ,
b1000 -
b10 +
b101000 4
b10 0
b10 1
0?
1A
b1100 <
b1000 /
b10100 :
b10100 9
b10100 8
b10100 7
b101 ;
b0 6
#560
b101 %
b101 )
b11011 $
b11011 (
b11101 '
b11101 .
0#
#580
b10 !
b10 C
b1 *
b11111 ,
b11110 -
b101 +
b100000 <
b10110 /
b1101100000 4
b0 0
b0 1
b10000111 :
b10000111 9
b10000111 8
b10000111 7
b10 6
