CPU/assert.v
`define assert(sig, val) \
    if (sig !== val) begin \
        $display("ASSERTION FAILED in %m: sig != %0d [original value %0d] in line %0d", val, sig, `__LINE__); \
        $finish; \
    end

CPU Test/REGISTER/reg.v
module reg_file(IN, OUT1, OUT2, INADDRESS, OUT1ADDRESS, OUT2ADDRESS, WRITEENABLE, CLK, RESET);
	//port declaration 
	//create a  8 bit input port
	input [31:0] IN;
	//create 3 3bit input ports (address of the registers)
	input [4:0] INADDRESS , OUT1ADDRESS , OUT2ADDRESS;
	//create 3  1bit input ports 
	input WRITEENABLE, CLK, RESET;

	
	//create 2 8 bit output reg for hold the result
	output reg [31:0] OUT1 ,OUT2;
	reg [31:0] register[31:0];
	integer i,wflag;   //flag for write  regiter and counting variable i
	
	//***********************************************
	//when the rising edge at clock
	always @(posedge CLK)
	begin
		if(WRITEENABLE == 1'b1 & RESET == 1'b0 ) //if writtble is high,when reset is high does not write)
		begin
			wflag = 1;
			#2 register[INADDRESS] = IN;     //write data into inaddress aftert 2s delay
			
		end
		if(wflag == 1) begin  //if register update it should read aftr clk posedge
			#2   //timeing delay for reading
			if(INADDRESS==OUT1ADDRESS || INADDRESS==OUT2ADDRESS)begin
			OUT1 = register[OUT1ADDRESS];	
			OUT2 = register[OUT2ADDRESS];
			wflag = 0;
			end
		end
	end

	always begin 
		
	@(posedge RESET) begin//when reset is high
			i =1; //i using as a flag to avoid reading the adress at this time
			#2  //time dealy for resetting registers
			for (i =0; i < 32 ;i = i + 1) begin
				register[i] = 32'd0;
			end
			  //i also used to read regiters after the reset
	end
	
		if(i==32)begin //after updating registers are reading
		#2 //time delay for reading (registers
		OUT1 = register[OUT1ADDRESS];	
		OUT2 = register[OUT2ADDRESS];
		
		end
	end
	
	always @(OUT1ADDRESS,OUT2ADDRESS) begin//when register address are updated registers are reading
	
		if(i != 1) begin  //if the reset happen at the same time does not run this
		#5 //time delay for reading (registers
		OUT1 = register[OUT1ADDRESS];	
		OUT2 = register[OUT2ADDRESS];
		end
	end			
endmodule

CPU Test/REGISTER/reg_testBench.v
`include "../assert.v"
`include "reg.v"

module reg_file_tb;

    reg CLK, RESET, WRITE_ENABLE;
    reg [31:0] WRITE_DATA;
    wire [31:0] DATA1,DATA2;
    reg [4:0] DATA1_ADDRESS, DATA2_ADDRESS, WRITE_ADDRESS;

    integer j;

    reg_file my_reg_file(WRITE_DATA, DATA1, DATA2, WRITE_ADDRESS, DATA1_ADDRESS, DATA2_ADDRESS, WRITE_ENABLE, CLK, RESET);

    initial begin
        RESET = 1'b0;
        WRITE_DATA = 32'd0;
        DATA1_ADDRESS = 5'd0;
        DATA2_ADDRESS = 5'd0;
        WRITE_ADDRESS = 5'd0;
        WRITE_ENABLE = 0;

        $dumpfile("reg_file_wavedata.vcd");
        $dumpvars(0, reg_file_tb);
        


        #1
        RESET = 1'b1;

        #5
        RESET = 1'b0;
        CLK = 1'b0;

        /* 
            TEST 1 starts here!
            Regfile module should able to write to specific register. 
            WRITE 10 to reg 1
        */
            WRITE_ADDRESS = 5'd1;
            WRITE_DATA = 32'd10;
            WRITE_ENABLE = 1'b1;

            @(posedge CLK) begin
                // wait for write to happen.
                #3;
                // read value of the address
                DATA1_ADDRESS = 5'd1;
                // wait for read to happen and check value
                #3;
                `assert(DATA1, 32'd10);
                $display("TEST 1 Passed!");

            end
        /* TEST 1 ends here! */

        #500
        $finish;
    end

    // clock genaration.
    always begin
        #4 CLK = ~CLK;
    end

endmodule

CPU Test/REGISTER/reg_file_wavedata.vcd
$date
	Tue Jul 06 22:29:36 2021
$end
$version
	Icarus Verilog
$end
$timescale
	1s
$end
$scope module reg_file_tb $end
$var wire 32 ! DATA2 [31:0] $end
$var wire 32 " DATA1 [31:0] $end
$var reg 1 # CLK $end
$var reg 5 $ DATA1_ADDRESS [4:0] $end
$var reg 5 % DATA2_ADDRESS [4:0] $end
$var reg 1 & RESET $end
$var reg 5 ' WRITE_ADDRESS [4:0] $end
$var reg 32 ( WRITE_DATA [31:0] $end
$var reg 1 ) WRITE_ENABLE $end
$scope module my_reg_file $end
$var wire 1 # CLK $end
$var wire 32 * IN [31:0] $end
$var wire 5 + INADDRESS [4:0] $end
$var wire 5 , OUT1ADDRESS [4:0] $end
$var wire 5 - OUT2ADDRESS [4:0] $end
$var wire 1 & RESET $end
$var wire 1 ) WRITEENABLE $end
$var reg 32 . OUT1 [31:0] $end
$var reg 32 / OUT2 [31:0] $end
$var integer 32 0 i [31:0] $end
$var integer 32 1 wflag [31:0] $end
$upscope $end
$upscope $end
$enddefinitions $end
#0
$dumpvars
bx 1
bx 0
bx /
bx .
b0 -
b0 ,
b0 +
b0 *
0)
b0 (
b0 '
0&
b0 %
b0 $
x#
bx "
bx !
$end
#1
b1 0
1&
#3
b100000 0
#5
b0 !
b0 /
b0 "
b0 .
#6
1)
b1010 (
b1010 *
b1 '
b1 +
0#
0&
#8
b1 1
1#
#11
b1 $
b1 ,
#12
b0 1
b1010 "
b1010 .
0#
#16
b1 1
1#
#20
b0 1
0#
#24
b1 1
1#
#28
b0 1
0#
#32
b1 1
1#
#36
b0 1
0#
#40
b1 1
1#
#44
b0 1
0#
#48
b1 1
1#
#52
b0 1
0#
#56
b1 1
1#
#60
b0 1
0#
#64
b1 1
1#
#68
b0 1
0#
#72
b1 1
1#
#76
b0 1
0#
#80
b1 1
1#
#84
b0 1
0#
#88
b1 1
1#
#92
b0 1
0#
#96
b1 1
1#
#100
b0 1
0#
#104
b1 1
1#
#108
b0 1
0#
#112
b1 1
1#
#116
b0 1
0#
#120
b1 1
1#
#124
b0 1
0#
#128
b1 1
1#
#132
b0 1
0#
#136
b1 1
1#
#140
b0 1
0#
#144
b1 1
1#
#148
b0 1
0#
#152
b1 1
1#
#156
b0 1
0#
#160
b1 1
1#
#164
b0 1
0#
#168
b1 1
1#
#172
b0 1
0#
#176
b1 1
1#
#180
b0 1
0#
#184
b1 1
1#
#188
b0 1
0#
#192
b1 1
1#
#196
b0 1
0#
#200
b1 1
1#
#204
b0 1
0#
#208
b1 1
1#
#212
b0 1
0#
#216
b1 1
1#
#220
b0 1
0#
#224
b1 1
1#
#228
b0 1
0#
#232
b1 1
1#
#236
b0 1
0#
#240
b1 1
1#
#244
b0 1
0#
#248
b1 1
1#
#252
b0 1
0#
#256
b1 1
1#
#260
b0 1
0#
#264
b1 1
1#
#268
b0 1
0#
#272
b1 1
1#
#276
b0 1
0#
#280
b1 1
1#
#284
b0 1
0#
#288
b1 1
1#
#292
b0 1
0#
#296
b1 1
1#
#300
b0 1
0#
#304
b1 1
1#
#308
b0 1
0#
#312
b1 1
1#
#316
b0 1
0#
#320
b1 1
1#
#324
b0 1
0#
#328
b1 1
1#
#332
b0 1
0#
#336
b1 1
1#
#340
b0 1
0#
#344
b1 1
1#
#348
b0 1
0#
#352
b1 1
1#
#356
b0 1
0#
#360
b1 1
1#
#364
b0 1
0#
#368
b1 1
1#
#372
b0 1
0#
#376
b1 1
1#
#380
b0 1
0#
#384
b1 1
1#
#388
b0 1
0#
#392
b1 1
1#
#396
b0 1
0#
#400
b1 1
1#
#404
b0 1
0#
#408
b1 1
1#
#412
b0 1
0#
#416
b1 1
1#
#420
b0 1
0#
#424
b1 1
1#
#428
b0 1
0#
#432
b1 1
1#
#436
b0 1
0#
#440
b1 1
1#
#444
b0 1
0#
#448
b1 1
1#
#452
b0 1
0#
#456
b1 1
1#
#460
b0 1
0#
#464
b1 1
1#
#468
b0 1
0#
#472
b1 1
1#
#476
b0 1
0#
#480
b1 1
1#
#484
b0 1
0#
#488
b1 1
1#
#492
b0 1
0#
#496
b1 1
1#
#500
b0 1
0#
#504
b1 1
1#
#508
b0 1
0#
#512
b1 1
1#
